sslproxies/__info__.py
sslproxies/__init__.py
sslproxies/sslproxies.py
sslproxies/classes/Proxy.py
sslproxies/classes/ProxyManager.py
sslproxies/classes/__init__.py
sslproxies-0.1.0.dist-info/LICENSE
sslproxies-0.1.0.dist-info/METADATA
sslproxies-0.1.0.dist-info/WHEEL
sslproxies-0.1.0.dist-info/top_level.txt
sslproxies-0.1.0.dist-info/RECORD
